adafruit_circuitpython_neotrellis-1.3.11.dist-info/licenses/LICENSE
adafruit_neotrellis/__init__.py
adafruit_neotrellis/multitrellis.py
adafruit_neotrellis/neotrellis.py
adafruit_circuitpython_neotrellis-1.3.11.dist-info/METADATA
adafruit_circuitpython_neotrellis-1.3.11.dist-info/WHEEL
adafruit_circuitpython_neotrellis-1.3.11.dist-info/top_level.txt
adafruit_circuitpython_neotrellis-1.3.11.dist-info/RECORD
