Metadata-Version: 2.4
Name: adafruit-circuitpython-neotrellis
Version: 1.3.11
Summary: CircuitPython library for using Adafruit NeoTrellis.
Author-email: Adafruit Industries <circuitpython@adafruit.com>
License: MIT
Project-URL: Homepage, https://github.com/adafruit/Adafruit_CircuitPython_NeoTrellis
Keywords: adafruit,neotrellis,neopixel,trellis,led,rgbsensor,hardware,micropython,circuitpython
Classifier: Intended Audience :: Developers
Classifier: Topic :: Software Development :: Libraries
Classifier: Topic :: Software Development :: Embedded Systems
Classifier: Topic :: System :: Hardware
Classifier: License :: OSI Approved :: MIT License
Classifier: Programming Language :: Python :: 3
License-File: LICENSE
Requires-Dist: Adafruit-Blinka
Requires-Dist: adafruit-circuitpython-seesaw
Provides-Extra: optional
Dynamic: license-file
